urouter/__init__.py
urouter/api.py
urouter/constants.py
urouter/exporters/__init__.py
urouter/exporters/aiohttp_exporter.py
urouter/exporters/starlette_exporter.py
urouter-0.1.2.dist-info/LICENSE
urouter-0.1.2.dist-info/METADATA
urouter-0.1.2.dist-info/WHEEL
urouter-0.1.2.dist-info/top_level.txt
urouter-0.1.2.dist-info/RECORD
