Metadata-Version: 2.1
Name: urouter
Version: 0.1.2
Summary: Router Configurator for you project.
Home-page: https://github.com/bruziev/urouter
Author: Bakhtiyor Ruziev
Author-email: bakhtiyor.ruziev@yandex.ru
License: MIT
Platform: UNKNOWN
Classifier: Development Status :: 4 - Beta
Classifier: Intended Audience :: Developers
Classifier: License :: OSI Approved :: MIT License
Classifier: Programming Language :: Python
Classifier: Programming Language :: Python :: 3.6
Classifier: Programming Language :: Python :: 3.7
Classifier: Programming Language :: Python :: 3.8
